{
  "$schema": "https://developer.microsoft.com/json-schemas/fabric/item/report/definition/visualContainer/2.5.0/schema.json",
  "name": "200c6d4db60c568561a7",
  "position": {
    "x": 667.77777777777771,
    "y": 443.33333333333331,
    "z": 9504,
    "height": 232.22222222222223,
    "width": 581.11111111111109,
    "tabOrder": 9004
  },
  "visual": {
    "visualType": "tableEx",
    "query": {
      "queryState": {
        "Values": {
          "projections": [
            {
              "field": {
                "Measure": {
                  "Expression": {
                    "SourceRef": {
                      "Entity": "_Measures"
                    }
                  },
                  "Property": "Page 1 - Ranking Fixed Rank"
                }
              },
              "queryRef": "_Measures.Page 1 - Ranking Fixed Rank",
              "nativeQueryRef": "Rank",
              "displayName": "Rank"
            },
            {
              "field": {
                "Column": {
                  "Expression": {
                    "SourceRef": {
                      "Entity": "City Lookup"
                    }
                  },
                  "Property": "City"
                }
              },
              "queryRef": "City Lookup.City",
              "nativeQueryRef": "City"
            },
            {
              "field": {
                "Measure": {
                  "Expression": {
                    "SourceRef": {
                      "Entity": "_Measures"
                    }
                  },
                  "Property": "Page 1 - Ranking Display Value"
                }
              },
              "queryRef": "_Measures.Page 1 - Ranking Display Value",
              "nativeQueryRef": "Value",
              "displayName": "Value"
            },
            {
              "field": {
                "Measure": {
                  "Expression": {
                    "SourceRef": {
                      "Entity": "_Measures"
                    }
                  },
                  "Property": "Page 1 - Ranking Display Sparkline"
                }
              },
              "queryRef": "_Measures.Page 1 - Ranking Display Sparkline",
              "nativeQueryRef": "10Y Trend",
              "displayName": "10Y Trend"
            },
            {
              "field": {
                "Measure": {
                  "Expression": {
                    "SourceRef": {
                      "Entity": "_Measures"
                    }
                  },
                  "Property": "Page 1 - Ranking YoY Display"
                }
              },
              "queryRef": "_Measures.Page 1 - Ranking YoY Display",
              "nativeQueryRef": "YoY",
              "displayName": "YoY"
            },
            {
              "field": {
                "Measure": {
                  "Expression": {
                    "SourceRef": {
                      "Entity": "_Measures"
                    }
                  },
                  "Property": "Page 1 - Ranking Display Gap"
                }
              },
              "queryRef": "_Measures.Page 1 - Ranking Display Gap",
              "nativeQueryRef": "Gap",
              "displayName": "Gap"
            }
          ]
        }
      }
    },
    "objects": {
      "columnFormatting": [
        {
          "properties": {
            "styleHeader": {
              "expr": {
                "Literal": {
                  "Value": "false"
                }
              }
            },
            "alignment": {
              "expr": {
                "Literal": {
                  "Value": "'Left'"
                }
              }
            }
          },
          "selector": {
            "metadata": "_Measures.Page 1 - Ranking Fixed Rank"
          }
        },
        {
          "properties": {
            "alignment": {
              "expr": {
                "Literal": {
                  "Value": "'Left'"
                }
              }
            },
            "styleHeader": {
              "expr": {
                "Literal": {
                  "Value": "false"
                }
              }
            }
          },
          "selector": {
            "metadata": "City Lookup.City"
          }
        },
        {
          "properties": {
            "alignment": {
              "expr": {
                "Literal": {
                  "Value": "'Center'"
                }
              }
            },
            "styleHeader": {
              "expr": {
                "Literal": {
                  "Value": "true"
                }
              }
            }
          },
          "selector": {
            "metadata": "_Measures.Page 1 - Ranking Display Value"
          }
        },
        {
          "properties": {
            "styleHeader": {
              "expr": {
                "Literal": {
                  "Value": "true"
                }
              }
            },
            "alignment": {
              "expr": {
                "Literal": {
                  "Value": "'Center'"
                }
              }
            }
          },
          "selector": {
            "metadata": "_Measures.Page 1 - Ranking Display Sparkline"
          }
        },
        {
          "properties": {
            "styleHeader": {
              "expr": {
                "Literal": {
                  "Value": "true"
                }
              }
            }
          },
          "selector": {
            "metadata": "_Measures.Page 1 - Ranking YoY Display"
          }
        },
        {
          "properties": {
            "styleHeader": {
              "expr": {
                "Literal": {
                  "Value": "true"
                }
              }
            },
            "alignment": {
              "expr": {
                "Literal": {
                  "Value": "'Center'"
                }
              }
            }
          },
          "selector": {
            "metadata": "_Measures.Page 1 - Ranking Display Gap"
          }
        }
      ],
      "total": [
        {
          "properties": {
            "totals": {
              "expr": {
                "Literal": {
                  "Value": "false"
                }
              }
            }
          }
        }
      ],
      "grid": [
        {
          "properties": {
            "gridVertical": {
              "expr": {
                "Literal": {
                  "Value": "true"
                }
              }
            },
            "rowPadding": {
              "expr": {
                "Literal": {
                  "Value": "1D"
                }
              }
            },
            "outlineColor": {
              "solid": {
                "color": {
                  "expr": {
                    "ThemeDataColor": {
                      "ColorId": 0,
                      "Percent": -0.3
                    }
                  }
                }
              }
            }
          }
        }
      ],
      "columnHeaders": [
        {
          "properties": {
            "fontSize": {
              "expr": {
                "Literal": {
                  "Value": "9D"
                }
              }
            },
            "autoSizeColumnWidth": {
              "expr": {
                "Literal": {
                  "Value": "true"
                }
              }
            }
          }
        }
      ]
    },
    "drillFilterOtherVisuals": true
  },
  "filterConfig": {
    "filters": [
      {
        "name": "c94bb5b40b4983302897",
        "field": {
          "Measure": {
            "Expression": {
              "SourceRef": {
                "Entity": "_Measures"
              }
            },
            "Property": "Page 1 - Ranking Fixed Rank"
          }
        },
        "type": "Advanced"
      },
      {
        "name": "8b8aab610ee3a5d69183",
        "field": {
          "Column": {
            "Expression": {
              "SourceRef": {
                "Entity": "City Lookup"
              }
            },
            "Property": "City"
          }
        },
        "type": "Categorical"
      },
      {
        "name": "d2225e401d40b36e8986",
        "field": {
          "Measure": {
            "Expression": {
              "SourceRef": {
                "Entity": "_Measures"
              }
            },
            "Property": "Page 1 - Ranking Display Value"
          }
        },
        "type": "Advanced"
      },
      {
        "name": "b8a1445741054c815ca0",
        "field": {
          "Measure": {
            "Expression": {
              "SourceRef": {
                "Entity": "_Measures"
              }
            },
            "Property": "Page 1 - Ranking Display Sparkline"
          }
        },
        "type": "Advanced"
      },
      {
        "name": "ea9808cdd0c0e1740d55",
        "field": {
          "Measure": {
            "Expression": {
              "SourceRef": {
                "Entity": "_Measures"
              }
            },
            "Property": "Page 1 - Ranking YoY Display"
          }
        },
        "type": "Advanced"
      },
      {
        "name": "01edec6e309e8e34908d",
        "field": {
          "Measure": {
            "Expression": {
              "SourceRef": {
                "Entity": "_Measures"
              }
            },
            "Property": "Page 1 - Ranking Display Gap"
          }
        },
        "type": "Advanced"
      }
    ]
  }
}